snipeit/Accessories.py
snipeit/Assets.py
snipeit/Categories.py
snipeit/Companies.py
snipeit/Components.py
snipeit/Consumables.py
snipeit/Departments.py
snipeit/FieldSets.py
snipeit/Fields.py
snipeit/Licenses.py
snipeit/Locations.py
snipeit/Maintenances.py
snipeit/Manufacturers.py
snipeit/Models.py
snipeit/Reports.py
snipeit/SnipeIT.py
snipeit/StatusLabels.py
snipeit/Users.py
snipeit/__init__.py
snipeit_api_controller-0.2.2.dist-info/LICENSE
snipeit_api_controller-0.2.2.dist-info/METADATA
snipeit_api_controller-0.2.2.dist-info/WHEEL
snipeit_api_controller-0.2.2.dist-info/top_level.txt
snipeit_api_controller-0.2.2.dist-info/RECORD
