Metadata-Version: 2.1
Name: snipeit-api-controller
Version: 0.2.2
Summary: SnipeIT API controller
Home-page: https://github.com/adfedotov/snipeit-api
Author: Andrei Fedotov
Author-email: anddfedotov@gmail.com
License: UNKNOWN
Platform: UNKNOWN
Classifier: Programming Language :: Python :: 3
Classifier: License :: OSI Approved :: MIT License
Classifier: Operating System :: OS Independent
License-File: LICENSE
Requires-Dist: requests
